itisi/__init__.py
itisi-0.1.4.dist-info/LICENSE
itisi-0.1.4.dist-info/METADATA
itisi-0.1.4.dist-info/WHEEL
itisi-0.1.4.dist-info/entry_points.txt
itisi-0.1.4.dist-info/top_level.txt
itisi-0.1.4.dist-info/RECORD
